galaxy/__init__.py
galaxy/project_galaxy_model_tools.py
galaxy/model_tools/__init__.py
galaxy/model_tools/apply_rules.xml
galaxy/model_tools/build_list.xml
galaxy/model_tools/data_fetch.xml
galaxy/model_tools/extract_dataset.xml
galaxy/model_tools/filter_empty_collection.xml
galaxy/model_tools/filter_failed_collection.xml
galaxy/model_tools/filter_from_file.xml
galaxy/model_tools/flatten_collection.xml
galaxy/model_tools/merge_collection.xml
galaxy/model_tools/relabel_from_file.xml
galaxy/model_tools/sort_collection_list.xml
galaxy/model_tools/tag_collection_from_file.xml
galaxy/model_tools/unzip_collection.xml
galaxy/model_tools/zip_collection.xml
galaxy/model_tools/imp_exp/__init__.py
galaxy/model_tools/imp_exp/exp_history_to_archive.xml
galaxy/model_tools/imp_exp/export_history.py
galaxy/model_tools/imp_exp/imp_history_from_archive.xml
galaxy/model_tools/imp_exp/unpack_tar_gz_archive.py
galaxy_model_tools-19.9.0.dev2.dist-info/LICENSE
galaxy_model_tools-19.9.0.dev2.dist-info/METADATA
galaxy_model_tools-19.9.0.dev2.dist-info/WHEEL
galaxy_model_tools-19.9.0.dev2.dist-info/entry_points.txt
galaxy_model_tools-19.9.0.dev2.dist-info/top_level.txt
galaxy_model_tools-19.9.0.dev2.dist-info/RECORD
