Metadata-Version: 2.1
Name: galaxy-model-tools
Version: 19.9.0.dev2
Summary: Galaxy Model Tools`
Home-page: https://github.com/galaxyproject/galaxy
Author: Galaxy Project and Community
Author-email: galaxy-committers@lists.galaxyproject.org
License: AFL
Keywords: galaxy
Platform: UNKNOWN
Classifier: Development Status :: 5 - Production/Stable
Classifier: Intended Audience :: Developers
Classifier: Environment :: Console
Classifier: License :: OSI Approved :: Academic Free License (AFL)
Classifier: Operating System :: POSIX
Classifier: Topic :: Software Development
Classifier: Topic :: Software Development :: Code Generators
Classifier: Topic :: Software Development :: Testing
Classifier: Natural Language :: English
Classifier: Programming Language :: Python :: 2
Classifier: Programming Language :: Python :: 2.7
Classifier: Programming Language :: Python :: 3.5
Classifier: Programming Language :: Python :: 3.6
Classifier: Programming Language :: Python :: 3.7
Requires-Dist: galaxy-data
